wsdp/__init__.py
wsdp/cli.py
wsdp/core.py
wsdp/algorithms/__init__.py
wsdp/algorithms/denoising.py
wsdp/algorithms/phase_calibration.py
wsdp/configs/__init__.py
wsdp/configs/model_params.json
wsdp/datasets/CSIDataset.py
wsdp/datasets/__init__.py
wsdp/models/__init__.py
wsdp/models/csi_model.py
wsdp/processors/__init__.py
wsdp/processors/base_processor.py
wsdp/readers/__init__.py
wsdp/readers/base.py
wsdp/readers/bfee_reader.py
wsdp/readers/elder_reader.py
wsdp/readers/xrf_reader.py
wsdp/structure/CSIData.py
wsdp/structure/CSIFrame.py
wsdp/structure/__init__.py
wsdp/utils/__init__.py
wsdp/utils/load_preset.py
wsdp/utils/resize.py
wsdp/utils/train_func.py
wsdp-0.0.6.dist-info/licenses/LICENSE
wsdp-0.0.6.dist-info/METADATA
wsdp-0.0.6.dist-info/WHEEL
wsdp-0.0.6.dist-info/entry_points.txt
wsdp-0.0.6.dist-info/top_level.txt
wsdp-0.0.6.dist-info/RECORD
