Metadata-Version: 2.4
Name: wsdp
Version: 0.0.6
Summary: A pipeline for large scale deep-learning based wireless sensing tasks, including preprocess, training and eval
Author-email: sdp_group <yuanhao.cui@bupt.edu.cn>
License-Expression: MIT AND (Apache-2.0 OR BSD-2-Clause)
Project-URL: Homepage, https://github.com/yuanhao-cui/Sensing-Data-Protocol
Project-URL: Bug Tracker, https://github.com/yuanhao-cui/Sensing-Data-Protocol/issues
Requires-Python: >=3.11
License-File: LICENSE
Requires-Dist: torch>=2.7.1
Requires-Dist: numpy>=2.4.1
Requires-Dist: matplotlib>=3.10.0
Requires-Dist: scikit_learn==1.8.0
Requires-Dist: seaborn==0.13.2
Requires-Dist: PyWavelets==1.8.0
Dynamic: license-file
